opensim_py/__init__.py
opensim_py/actuators.py
opensim_py/analyses.py
opensim_py/common.py
opensim_py/examplecomponents.py
opensim_py/moco.py
opensim_py/report.py
opensim_py/simbody.py
opensim_py/simulation.py
opensim_py/tools.py
opensim_py/version.py
opensim_py-0.0.0b0.dist-info/LICENSE
opensim_py-0.0.0b0.dist-info/METADATA
opensim_py-0.0.0b0.dist-info/WHEEL
opensim_py-0.0.0b0.dist-info/top_level.txt
opensim_py-0.0.0b0.dist-info/RECORD
