Metadata-Version: 2.1
Name: opensim-py
Version: 0.0.0b0
Summary: An attempt to create a python package for opensim
Home-page: https://github.com/basgoncalves/opensim_py.git
Author: Bas
Author-email: basilio.goncalves7@gmail.com
License: UNKNOWN
Platform: UNKNOWN
Classifier: Programming Language :: Python :: 3
Classifier: License :: OSI Approved :: MIT License
Classifier: Operating System :: OS Independent
Requires-Python: >=3.8
Requires-Dist: numpy
Requires-Dist: numpy-stl
Requires-Dist: pandas
Requires-Dist: c3d
Requires-Dist: pyperclip
Requires-Dist: customtkinter
Requires-Dist: matplotlib
Requires-Dist: febio-python
Requires-Dist: vedo
Requires-Dist: scipy
Requires-Dist: scikit-learn
